dowml/__init__.py
dowml/interactive.py
dowml/lib.py
dowml/dowmllib/__init__.py
dowml-1.9.0.dist-info/LICENSE
dowml-1.9.0.dist-info/METADATA
dowml-1.9.0.dist-info/WHEEL
dowml-1.9.0.dist-info/entry_points.txt
dowml-1.9.0.dist-info/top_level.txt
dowml-1.9.0.dist-info/RECORD
