Metadata-Version: 2.1
Name: dowml
Version: 1.9.0
Summary: Submit existing Decision Optimization instances to WML
Home-page: https://github.com/nodet/dowml
Author: Xavier Nodet
Author-email: xavier.nodet@gmail.com
License: Apache License 2.0
Classifier: Programming Language :: Python :: 3.8
Classifier: License :: OSI Approved :: Apache Software License
Classifier: Operating System :: OS Independent
Classifier: Development Status :: 4 - Beta
Classifier: Environment :: Console
Classifier: Intended Audience :: Developers
Classifier: Topic :: Scientific/Engineering :: Artificial Intelligence
Classifier: Topic :: Software Development :: Libraries
Requires-Python: >=3.8
License-File: LICENSE
Requires-Dist: ibm-watson-machine-learning (>=1.0.95.1)
